taurex_madhuseager2009/.DS_Store
taurex_madhuseager2009/__init__.py
taurex_madhuseager2009/main.py
taurex_madhuseager2009-0.0.4.dist-info/WHEEL
taurex_madhuseager2009-0.0.4.dist-info/entry_points.txt
taurex_madhuseager2009-0.0.4.dist-info/METADATA
taurex_madhuseager2009-0.0.4.dist-info/RECORD
