Metadata-Version: 2.1
Name: taurex-madhuseager2009
Version: 0.0.4
Summary: MadhuSeager2009
Home-page: https://github.com/michellebieger/MadhuSeager2009
License: GPL-3.0
Author: M. F. Bieger
Author-email: mb987@exeter.ac.uk
Requires-Python: >=3.8,<4.0
Classifier: Development Status :: 1 - Planning
Classifier: License :: OSI Approved :: GNU General Public License v3 (GPLv3)
Classifier: Programming Language :: Python :: 3
Classifier: Programming Language :: Python :: 3.8
Classifier: Programming Language :: Python :: 3.9
Classifier: Programming Language :: Python :: 3.10
Classifier: Programming Language :: Python :: 3.11
Requires-Dist: taurex (>=3.1.1a0,<4.0.0)
Project-URL: Repository, https://github.com/michellebieger/MadhuSeager2009
